fl_henchman-0.0.4.dist-info/METADATA
fl_henchman-0.0.4.dist-info/RECORD
fl_henchman-0.0.4.dist-info/WHEEL
fl_henchman-0.0.4.dist-info/top_level.txt
henchman/__init__.py
henchman/diagnostics.py
henchman/learning.py
henchman/plotting.py
henchman/selection.py
