Metadata-Version: 2.1
Name: fl-henchman
Version: 0.0.4
Summary: A collection of utility functions for making demo notebooks.
Home-page: https://github.com/featurelabs/henchman
Author: Feature Labs Team
Author-email: team@featurelabs.com
License: BSD 3-clause
Keywords: henchman
Platform: UNKNOWN
Classifier: Development Status :: 3 - Alpha
Classifier: Intended Audience :: Developers
Classifier: Natural Language :: English
Classifier: Programming Language :: Python :: 2
Classifier: Programming Language :: Python :: 2.7
Classifier: Programming Language :: Python :: 3
Classifier: Programming Language :: Python :: 3.6
Classifier: Programming Language :: Python :: 3.7
Requires-Dist: ipython (>=5.4)
Requires-Dist: numpy (>=1.13.3)
Requires-Dist: scipy (>=1.0.0)
Requires-Dist: scikit-learn (>=0.19.1)
Requires-Dist: pandas (>=0.20.3)
Requires-Dist: bokeh (>=0.12.16)
Requires-Dist: networkx (>=2.1)
Requires-Dist: tqdm (>=4.10.0)
